{
  "_fv": 66,
  "_type": "recipe",
  "definition": {
    "recipeType": "Crafting",
    "recipeRetstackSize": 1,
    "group": "",
    "cookingBookCategory": "MISC",
    "xpReward": 0.0,
    "cookingTime": 200,
    "craftingBookCategory": "MISC",
    "recipeShapeless": true,
    "recipeSlots": [
      {
        "value": "Blocks.WAXED_COPPER_BLOCK"
      },
      {
        "value": "Blocks.EMERALD_BLOCK"
      },
      {
        "value": "Blocks.WAXED_COPPER_BLOCK"
      },
      {
        "value": "Blocks.GOLD_BLOCK"
      },
      {
        "value": "Blocks.IRON_BLOCK"
      },
      {
        "value": "Blocks.DIAMOND_BLOCK"
      },
      {
        "value": "Blocks.WAXED_COPPER_BLOCK"
      },
      {
        "value": "Blocks.LAPIS_BLOCK"
      },
      {
        "value": "Blocks.WAXED_COPPER_BLOCK"
      }
    ],
    "recipeReturnStack": {
      "value": "CUSTOM:RanahiroIngot"
    },
    "name": "ranahiro_ingot_recipe",
    "namespace": "mod"
  }
}